setup.cfg
setup.py
econometrics_tests_statistics/__init__.py
econometrics_tests_statistics/main.py
econometrics_tests_statistics.egg-info/PKG-INFO
econometrics_tests_statistics.egg-info/SOURCES.txt
econometrics_tests_statistics.egg-info/dependency_links.txt
econometrics_tests_statistics.egg-info/not-zip-safe
econometrics_tests_statistics.egg-info/requires.txt
econometrics_tests_statistics.egg-info/top_level.txt