Metadata-Version: 2.1
Name: econometrics-tests-statistics
Version: 1.3
Summary: Numerical methods
Author-email: vovalagutov1111@yandex.ru
